Workbook

Sheet 企業名單
A1: 編號 | B1: 公司名稱 | C1: 產業別 | D1: SBTi | E1: RE100 | F1: EV100 | G1: EP100 | H1: 排碳大戶 | I1: 公司網址 | J1: 公司簡介
A2: 7 | B2: 三芳化學工業股份有限公司 | C2: 化工與生技醫療業 | D2: Committed to set SBT target | E2: X | F2: X | G2: X | H2: {=XLOOKUP(B2,'所有排碳大戶_2024_300'!A:A,'所有排碳大戶_2024_300'!A:A)} -> 三芳化學工業股份有限公司 | I2: https://www.sanfang.com/ | J2: 1973年三芳化學公司成立於高雄。三芳為臺灣第一家使用濕式PU製程於人工皮革的公司，經長期的市場變革、研發投入與產品進化。目前主要產品為人工皮革、科技薄膜、纖維、功能紗線與特殊不織布等。生產基地包含臺灣(仁武)到大陸(黃江)、越南(巴地頭頓省)到印尼。 採取行動保護環境，如更換低能耗設備、引進可再生能源、優化生產流程減少能源浪費、採用綠色材料、培訓員工環保意識、展開節水行動、進行碳足跡評估、改變工作方式降低交通物流對環境的影響。
A3: 12 | B3: 上銀科技股份有限公司 | C3: 科技與製造業 | D3: Aligned to 1.5°C | E3: X | F3: X | G3: X | H3: {=XLOOKUP(B3,'所有排碳大戶_2024_300'!A:A,'所有排碳大戶_2024_300'!A:A)} -> 上銀科技股份有限公司 | I3: https://www.hiwin.tw/ | J3: 創 立於 1989 年，傳動控制產品與系統科技產品的專業製造者，海外子、孫公司有德國、日本、美國、義大利、瑞士、捷克、法國、新加坡、韓國、中國 蘇州，研發中心則位於臺灣台中、日本東京、德國歐芬堡、以色列。 上銀科技身為國際企業與地球公民的一份子，積極響應國際2050年淨零排放趨勢，設定短中長期減碳目標與路徑，並以提高能源效率、創新低碳產品、循環經濟減廢、建置再生能源四大核心策略全面展開減碳行動。
A4: 24 | B4: 中華紙漿股份有限公司 | C4: 科技與製造業 | D4: Committed to set SBT target | E4: X | F4: X | G4: X | H4: {=XLOOKUP(B4,'所有排碳大戶_2024_300'!A:A,'所有排碳大戶_2024_300'!A:A)} -> 中華紙漿股份有限公司 | I4: http://www.chp.com.tw/ | J4: 中華紙漿為臺灣紙漿及紙品加工製造為主要業務的企業，主要產品有短纖闊葉樹紙漿、文化用紙、紙板與特殊紙。 通過眾多綠色產品及其他認證，包含：ISO 90001、ISO 14001、ISO 14064、ISO 50001、ISO 45001。 企業獲頒多項永續相關獎項，包含「亞洲企業社會責任獎-綠色領導獎」、TCSA 臺灣企業永續獎 –Top 50 企業永續獎、CSR 報告書銅獎、台北市環保局「綠色採購績優單位」、「空氣品質淨化區優良認養單位」、「榮獲節能減碳行動標章」、「節能減碳行動標章」等。
A5: 15 | B5: 元太科技工業股份有限公司 | C5: 科技與製造業 | D5: Aligned to 1.5°C | E5: V | F5: X | G5: V | H5: {=XLOOKUP(B5,'所有排碳大戶_2024_300'!A:A,'所有排碳大戶_2024_300'!A:A)} -> 元太科技工業股份有限公司 | I5: https://tw.eink.com/ | J5: • 元太科技據點遍佈中國大陸、日本、韓國及美國等地。其主要產品電子紙，可取代一次性用紙並具備可長期重覆使用的特性，大幅降低ㄧ次性紙張的耗用，近 5 年間帶來減少 237 萬公噸 CO2 的效益，致力實踐 ESG永續發展目標。
A6: 27 | B6: 友達光電股份有限公司 | C6: 科技與製造業 | D6: Aligned to 1.5°C | E6: V | F6: X | G6: X | H6: {=XLOOKUP(B6,'所有排碳大戶_2024_300'!A:A,'所有排碳大戶_2024_300'!A:A)} -> 友達光電股份有限公司 | I6: https://www.auo.com/ | J6: • 友達以發展先進顯示技術與產品起家，並以深厚的顯示技術為核心，結合 AIoT 致力成為各場域的解決方案商。 • 以永續經營為目標，將綠色承諾落實於生產流程、廠房建置、能源回收再利用等各環節。 • 自 2010 年起連續入選道瓊世界永續性指數成份股；永續報告書獲得「亞洲永續報告獎」11 項獎項肯定；並榮獲臺灣永續獎及全球永續獎 14 項殊榮。
A7: 34 | B7: 世界先進積體電路股份有限公司 | C7: 科技與製造業 | D7: X | E7: V | F7: X | G7: X | H7: {=XLOOKUP(B7,'所有排碳大戶_2024_300'!A:A,'所有排碳大戶_2024_300'!A:A)} -> 世界先進積體電路股份有限公司 | I7: https://www.vis.com.tw/tc/ | J7: VIS是一家領先的專業 IC 代工服務提供商，總部位於臺灣。在全球擁有五座8吋晶圓廠，總部在新竹科學園區，在北美、中國大陸、新加坡均有子公司，月產能約為 262,000 片晶圓，到 2022 年員工總數將超過 6,000 人，目標成為「特殊積體電路製造服務」的領導廠商。 深知企業永續與環境永續，公司勢必得邁向低碳轉型，並以負責任的態度，規畫出從合規（Compliance）逐步邁向承諾（Commitment）的永續藍圖，最終達成2050年淨零排放的倡議目標。
A8: 32 | B8: 可成科技股份有限公司 | C8: 科技與製造業 | D8: Aligned to 1.5°C | E8: X | F8: X | G8: X | H8: {=XLOOKUP(B8,'所有排碳大戶_2024_300'!A:A,'所有排碳大戶_2024_300'!A:A)} -> 可成科技股份有限公司 | I8: https://www.catcher-group.com/tw/ | J8: 可成科技以鋁合金壓鑄件起家，於1988年開始研究鎂合金壓鑄技術，1994年與臺灣筆記型電腦(筆電)品牌大廠合作開發筆電鎂合金壓鑄件，並於1998年起陸續贏得歐美筆電大廠認證。 可成科技通過眾多綠色產品及其他認證，包含：ISO 9001、ISO 9002、ISO 14001、 ISO 14064及ISO 45001：2018、TTQS、IATF 16949、ISO 13485。
A9: 43 | B9: 台塑勝高科技股份有限公司 | C9: 科技與製造業 | D9: Well-below 2°C | E9: X | F9: X | G9: X | H9: {=XLOOKUP(B9,'所有排碳大戶_2024_300'!A:A,'所有排碳大戶_2024_300'!A:A)} -> 台塑勝高科技股份有限公司 | I9: https://www.fstech.com.tw/ | J9: 台塑勝高為台塑集團與SUMCO的合資公司，母公司Sumco為全球第二大半導體矽晶圓廠，其業務主要為8吋及12吋矽晶圓生產製造，同時為具備拉晶及晶圓的製造廠。 通過眾多綠色產品及其他認證，包含ISO 26000、ISO 14001、ISO 14064-1、ISO 45001、TOSHMS(CNS 45001)
A10: 178 | B10: 台灣化學纖維股份有限公司 | C10: 化工與生技醫療業 | D10: Well-below 2°C | E10: X | F10: X | G10: X | H10: {=XLOOKUP(B10,'所有排碳大戶_2024_300'!A:A,'所有排碳大戶_2024_300'!A:A)} -> 台灣化學纖維股份有限公司 | I10: https://www.fcfc.com.tw/ | J10: 臺灣化纖為台塑集團主要成員之一。原先從事紡織、纖維一貫產品之製銷，於1987年起，陸續加入PS、ABS等塑膠產品，投資六輕後，轉型為以生產石化、塑膠產品為主之事業體。為全球第二大SM製造商、全球第三大ABS、合成酚製造商、全球第五大PS製造商、全球第七大芳香烴、PTA、聚碳酸酯樹酯製造商。 公司主要生產據點在臺灣、中國大陸及越南，營業銷售服務則遍及各大洲。國內及中國大陸銷售市場占比最高，其次是東南亞國家。臺灣總員工數為5,166人。
A11: 177 | B11: 台灣水泥股份有限公司 | C11: 化工與生技醫療業 | D11: Aligned to 1.5°C | E11: X | F11: X | G11: V | H11: {=XLOOKUP(B11,'所有排碳大戶_2024_300'!A:A,'所有排碳大戶_2024_300'!A:A)} -> 台灣水泥股份有限公司 | I11: https://www.taiwancement.com/tw/ | J11: • 以水泥生產為主的礦業公司，「資源循環、綠色能源、低碳水泥」為三大核心事業 ；未來台泥將運用創新科技與思維，開發新能源，朝 「零廢棄、零污染、零排放」之循環經濟、創造永續企業的新價值前進。 • 自 2020 年起連續三年榮獲 Sustainalytics ESG Top-Rated 頂級企業徽章；2021 年 CDP 碳 揭 露 計 畫 榮 獲 B 等；榮 獲 GCSA 全 球 企 業 永 續 獎 以 及TCSA 臺灣企業永續獎等共 11 項肯定。
A12: 180 | B12: 台灣塑膠工業股份有限公司 | C12: 化工與生技醫療業 | D12: Well-below 2°C | E12: X | F12: X | G12: X | H12: {=XLOOKUP(B12,'所有排碳大戶_2024_300'!A:A,'所有排碳大戶_2024_300'!A:A)} -> 台灣塑膠工業股份有限公司 | I12: https://www.fpc.com.tw/ | J12: 臺灣塑膠工業(台塑)目前所經營事業包括煉油、石化原料、塑膠加工、纖維、紡織、鋼鐵、電子、汽電、機械、海陸運輸、生物科技等事業。截至2021年底擁有生產事業包括台塑、南亞、台化、台塑石化及台塑河靜鋼鐵等海內外關係企業逾百餘家公司，員工總人數逾11萬人，資本額8,402億元，資產總值逾4兆元。 為世界最大的PVC粉、塑膠加工、纖維、乙烯及丙烯輕油裂解、化學品生產廠商之一。而在產能方面，銅箔基板、玻纖絲與玻纖布、環氧樹脂、銅箔等產品皆居世界前三位，亦為臺灣DRAM產能第一之企業，並大量投入遠端監控等智慧資訊科技開發、及對環境友善的綠色製程與產品研究。 其企業通過眾多綠色產品及其他認證，包含：ISO 90001、ISO 14001、ISO 14064-1、ISO 45001、CNS45001。
A13: 182 | B13: 台灣積體電路製造股份有限公司 | C13: 科技與製造業 | D13: X | E13: V | F13: X | G13: X | H13: {=XLOOKUP(B13,'所有排碳大戶_2024_300'!A:A,'所有排碳大戶_2024_300'!A:A)} -> 台灣積體電路製造股份有限公司 | I13: https://www.tsmc.com/ | J13: • 台積電專注提升本業核心能力，積極落實五大永續角色 ( 綠色製造、建立責任供應鏈、多元包容職場、人才培育、弱勢關懷 )，從上游採購、公司營運與客戶使用三大階段，帶動半導體產業具體實踐聯合國永續發展目標 (Sustainable Development Goals, SDGs)。 • 承諾於 2050 年全球營運 100% 使用再生能源，使用電力所間接排放的二氧化碳全部歸零。
... A200: 199 | B200: 寶成子公司 Myanmar Pou Chen Company Limited | C200: 科技與製造業 | D200: Committed to set SBT target | E200: X | F200: X | G200: X | H200: {=XLOOKUP(B200,'所有排碳大戶_2024_300'!A:A,'所有排碳大戶_2024_300'!A:A)} -> #N/A | I200: https://www.pouchen.com/ | J200: 寶成工業股份有限公司成立於1969年，初期主要從事塑膠鞋之生產製造及出口，爾後開始專注於運動鞋及休閒鞋之研發製造，並於近年積極發展運動用品通路業務。發展至今，寶成工業已轉型為產業控股公司的方式運作，藉由旗下轉投資公司致力於「製鞋」及「通路」二大核心業務之經營。營運據點遍布臺灣、中國大陸、印尼、越南、孟加拉、柬埔寨及緬甸等地。 秉持著環保與生產平衡兼顧原則，致力於下列環境保護措施： 導入環境管理系統有效運作，落實環境污染防治與衝擊管理，以促進環境資源的永續性。 遵守並符合環保相關法規及其他要求事項，據以制定相關標準作業程序且落實執行。 優化生產製程，推動清潔生產、減少污染排放、落實污染控制與管理，定期檢測稽查。 減少危害性物質使用，推動工業減廢、資源回收再利用與節能減碳措施，以持續提升企業環境保護績效。 加強教育訓練，提升全員環保認知，以徹底落實環保責任。

Sheet 說明
A1: 臺灣加入國際減碳倡議企業動態儀表板
A3: 資料來源：綠色貿易資訊網（greentrade.org.tw）
A4: 網址：https://www.greentrade.org.tw/content/臺灣加入國際減碳倡議企業動態儀表板
A5: 執行單位：經濟部國際貿易署 / 中華民國對外貿易發展協會 / 工業技術研究院
A6: 資料最後更新時間：2026/04/25（依網站標示）
A7: 本檔抓取範圍：第1頁至第10頁，共計 199 筆企業
A9: 【欄位說明】
A10: 公司名稱、產業別：依網站列示
A11: SBTi（科學基礎減量目標倡議）：分為 Aligned to 1.5°C、Well-below 2°C、Committed to set SBT target，未承諾者標記為 X
A12: RE100：2050 年前 100% 使用再生能源（綠電）—— V 表示已加入承諾
A13: EV100：2030 年前車隊 100% 電動化 —— V 表示已加入承諾
A14: EP100：能源效率提升 100% —— V 表示已加入承諾
... A22: 2. 統計摘要：依產業別與 SBTi 等級之彙總統計

Sheet 統計摘要
A1: 依產業別統計（V 數量）
A3: 產業別 | B3: 企業數 | C3: SBTi（已承諾或達標） | D3: RE100 | E3: EV100 | F3: EP100
A4: 科技與製造業 | B4: 121 | C4: 115 | D4: 21 | E4: 1 | F4: 1
A5: 化工與生技醫療業 | B5: 33 | C5: 27 | D5: 8 | E5: 0 | F5: 3
A6: 金融業 | B6: 21 | C6: 21 | D6: 3 | E6: 0 | F6: 0
A7: 電信業 | B7: 3 | C7: 3 | D7: 3 | E7: 2 | F7: 0
A8: 其他 | B8: 21 | C8: 20 | D8: 1 | E8: 0 | F8: 1
A9: 合計 | B9: =SUM(B4:B8) -> 199 | C9: =SUM(C4:C8) -> 186 | D9: =SUM(D4:D8) -> 36 | E9: =SUM(E4:E8) -> 3 | F9: =SUM(F4:F8) -> 5
A12: SBTi 等級分布
A14: SBTi 等級 | B14: 企業數 | C14: 占比
A15: Aligned to 1.5°C | B15: 111 | C15: =B15/SUM($B$15:$B$18) -> 0.55778894
A16: Well-below 2°C | B16: 13 | C16: =B16/SUM($B$15:$B$18) -> 0.065326633
A17: Committed to set SBT target | B17: 62 | C17: =B17/SUM($B$15:$B$18) -> 0.31155779
A18: X（未承諾 SBTi，僅參與其他倡議） | B18: 13 | C18: =B18/SUM($B$15:$B$18) -> 0.065326633

Sheet 2025年永續獎
A1: 公司 | B1: SBTi | C1: RE100 | D1: EV100 | E1: EP100
A2: 上銀科技股份有限公司 | B2: {=XLOOKUP($A2,'企業名單'!$B:$B,'企業名單'!D:D)} -> Aligned to 1.5°C | C2: {=XLOOKUP($A2,'企業名單'!$B:$B,'企業名單'!E:E)} -> X | D2: {=XLOOKUP($A2,'企業名單'!$B:$B,'企業名單'!F:F)} -> X | E2: {=XLOOKUP($A2,'企業名單'!$B:$B,'企業名單'!G:G)} -> X | H2: 台灣企業永續獎 台灣100大永續典範企業獎
A3: 元太科技工業股份有限公司 | B3: {=XLOOKUP($A3,'企業名單'!$B:$B,'企業名單'!D:D)} -> Aligned to 1.5°C | C3: {=XLOOKUP($A3,'企業名單'!$B:$B,'企業名單'!E:E)} -> V | D3: {=XLOOKUP($A3,'企業名單'!$B:$B,'企業名單'!F:F)} -> X | E3: {=XLOOKUP($A3,'企業名單'!$B:$B,'企業名單'!G:G)} -> V | H3: 台灣企業永續獎 台灣十大永續典範企業獎 | I3: 台灣企業永續獎 單項績效 - 氣候領袖獎 | J3: 大型企業
A4: 友達光電股份有限公司 | B4: {=XLOOKUP($A4,'企業名單'!$B:$B,'企業名單'!D:D)} -> Aligned to 1.5°C | C4: {=XLOOKUP($A4,'企業名單'!$B:$B,'企業名單'!E:E)} -> V | D4: {=XLOOKUP($A4,'企業名單'!$B:$B,'企業名單'!F:F)} -> X | E4: {=XLOOKUP($A4,'企業名單'!$B:$B,'企業名單'!G:G)} -> X | H4: 台灣企業永續獎 台灣100大永續典範企業獎 | I4: 台灣企業永續獎 單項績效 - 氣候領袖獎
A5: 日月光半導體製造股份有限公司 | B5: Aligned to 1.5°C | C5: X | D5: X | E5: X | F5: 企業類永續發展獎（高雄廠）
A6: 亞洲水泥股份有限公司 | B6: {=XLOOKUP($A6,'企業名單'!$B:$B,'企業名單'!D:D)} -> Aligned to 1.5°C | C6: {=XLOOKUP($A6,'企業名單'!$B:$B,'企業名單'!E:E)} -> X | D6: {=XLOOKUP($A6,'企業名單'!$B:$B,'企業名單'!F:F)} -> X | E6: {=XLOOKUP($A6,'企業名單'!$B:$B,'企業名單'!G:G)} -> X | G6: 綜合績效——傳統產業 | H6: 台灣企業永續獎 台灣100大永續典範企業獎
A7: 奇美實業股份有限公司 | B7: {=XLOOKUP($A7,'企業名單'!$B:$B,'企業名單'!D:D)} -> Aligned to 1.5°C | C7: {=XLOOKUP($A7,'企業名單'!$B:$B,'企業名單'!E:E)} -> X | D7: {=XLOOKUP($A7,'企業名單'!$B:$B,'企業名單'!F:F)} -> X | E7: {=XLOOKUP($A7,'企業名單'!$B:$B,'企業名單'!G:G)} -> X | F7: 企業類永續發展獎
A8: 新唐科技股份有限公司 | B8: {=XLOOKUP($A8,'企業名單'!$B:$B,'企業名單'!D:D)} -> Aligned to 1.5°C | C8: {=XLOOKUP($A8,'企業名單'!$B:$B,'企業名單'!E:E)} -> X | D8: {=XLOOKUP($A8,'企業名單'!$B:$B,'企業名單'!F:F)} -> X | E8: {=XLOOKUP($A8,'企業名單'!$B:$B,'企業名單'!G:G)} -> X | H8: 台灣企業永續獎 台灣100大永續典範企業獎
A9: 聯華電子股份有限公司 | B9: {=XLOOKUP($A9,'企業名單'!$B:$B,'企業名單'!D:D)} -> Aligned to 1.5°C | C9: {=XLOOKUP($A9,'企業名單'!$B:$B,'企業名單'!E:E)} -> V | D9: {=XLOOKUP($A9,'企業名單'!$B:$B,'企業名單'!F:F)} -> X | E9: {=XLOOKUP($A9,'企業名單'!$B:$B,'企業名單'!G:G)} -> X | H9: 台灣企業永續獎 台灣十大永續典範企業獎
A10: 中華紙漿股份有限公司 | B10: {=XLOOKUP($A10,'企業名單'!$B:$B,'企業名單'!D:D)} -> Committed to set SBT target | C10: {=XLOOKUP($A10,'企業名單'!$B:$B,'企業名單'!E:E)} -> X | D10: {=XLOOKUP($A10,'企業名單'!$B:$B,'企業名單'!F:F)} -> X | E10: {=XLOOKUP($A10,'企業名單'!$B:$B,'企業名單'!G:G)} -> X | G10: 傑出方案——低碳營運 | H10: 台灣企業永續獎 台灣永續企業績優獎
A11: 遠東新世紀股份有限公司 | B11: {=XLOOKUP($A11,'企業名單'!$B:$B,'企業名單'!D:D)} -> Committed to set SBT target | C11: {=XLOOKUP($A11,'企業名單'!$B:$B,'企業名單'!E:E)} -> X | D11: {=XLOOKUP($A11,'企業名單'!$B:$B,'企業名單'!F:F)} -> X | E11: {=XLOOKUP($A11,'企業名單'!$B:$B,'企業名單'!G:G)} -> X | I11: 台灣企業永續獎 單項績效 - 氣候領袖獎
A12: 環球晶圓股份有限公司 | B12: {=XLOOKUP($A12,'企業名單'!$B:$B,'企業名單'!D:D)} -> Committed to set SBT target | C12: {=XLOOKUP($A12,'企業名單'!$B:$B,'企業名單'!E:E)} -> V | D12: {=XLOOKUP($A12,'企業名單'!$B:$B,'企業名單'!F:F)} -> X | E12: {=XLOOKUP($A12,'企業名單'!$B:$B,'企業名單'!G:G)} -> X | H12: 台灣企業永續獎 台灣100大永續典範企業獎
A13: 南亞科技股份有限公司 | B13: {=XLOOKUP($A13,'企業名單'!$B:$B,'企業名單'!D:D)} -> Well-below 2°C | C13: {=XLOOKUP($A13,'企業名單'!$B:$B,'企業名單'!E:E)} -> X | D13: {=XLOOKUP($A13,'企業名單'!$B:$B,'企業名單'!F:F)} -> X | E13: {=XLOOKUP($A13,'企業名單'!$B:$B,'企業名單'!G:G)} -> X | H13: 台灣企業永續獎 台灣100大永續典範企業獎 | I13: 台灣企業永續獎 單項績效 - 氣候領袖獎
A14: 群創光電股份有限公司 | B14: {=XLOOKUP($A14,'企業名單'!$B:$B,'企業名單'!D:D)} -> Well-below 2°C | C14: {=XLOOKUP($A14,'企業名單'!$B:$B,'企業名單'!E:E)} -> X | D14: {=XLOOKUP($A14,'企業名單'!$B:$B,'企業名單'!F:F)} -> X | E14: {=XLOOKUP($A14,'企業名單'!$B:$B,'企業名單'!G:G)} -> X | H14: 台灣企業永續獎 台灣100大永續典範企業獎 | I14: 台灣企業永續獎 單項績效 - 氣候領袖獎
A15: 福懋科技股份有限公司 | B15: {=XLOOKUP($A15,'企業名單'!$B:$B,'企業名單'!D:D)} -> Well-below 2°C | C15: {=XLOOKUP($A15,'企業名單'!$B:$B,'企業名單'!E:E)} -> X | D15: {=XLOOKUP($A15,'企業名單'!$B:$B,'企業名單'!F:F)} -> X | E15: {=XLOOKUP($A15,'企業名單'!$B:$B,'企業名單'!G:G)} -> X | H15: 台灣企業永續獎 台灣100大永續典範企業獎 | I15: 台灣企業永續獎 單項績效 - 氣候領袖獎
A16: 世界先進積體電路股份有限公司 | B16: {=XLOOKUP($A16,'企業名單'!$B:$B,'企業名單'!D:D)} -> X | C16: {=XLOOKUP($A16,'企業名單'!$B:$B,'企業名單'!E:E)} -> V | D16: {=XLOOKUP($A16,'企業名單'!$B:$B,'企業名單'!F:F)} -> X | E16: {=XLOOKUP($A16,'企業名單'!$B:$B,'企業名單'!G:G)} -> X | H16: 台灣企業永續獎 台灣十大永續典範企業獎
A17: 台灣積體電路製造股份有限公司 | B17: {=XLOOKUP($A17,'企業名單'!$B:$B,'企業名單'!D:D)} -> X | C17: {=XLOOKUP($A17,'企業名單'!$B:$B,'企業名單'!E:E)} -> V | D17: {=XLOOKUP($A17,'企業名單'!$B:$B,'企業名單'!F:F)} -> X | E17: {=XLOOKUP($A17,'企業名單'!$B:$B,'企業名單'!G:G)} -> X | F17: 企業類永續發展獎（先進封測三廠） | H17: 台灣企業永續獎 台灣十大永續典範企業獎 | I17: 台灣企業永續獎 單項績效 - 氣候領袖獎
A18: 力成科技股份有限公司 | B18: {=XLOOKUP($A18,'企業名單'!$B:$B,'企業名單'!D:D)} -> #N/A | C18: {=XLOOKUP($A18,'企業名單'!$B:$B,'企業名單'!E:E)} -> #N/A | D18: {=XLOOKUP($A18,'企業名單'!$B:$B,'企業名單'!F:F)} -> #N/A | E18: {=XLOOKUP($A18,'企業名單'!$B:$B,'企業名單'!G:G)} -> #N/A | H18: 台灣企業永續獎 台灣100大永續典範企業獎
A19: 中國石油化學工業開發股份有限公司 | B19: {=XLOOKUP($A19,'企業名單'!$B:$B,'企業名單'!D:D)} -> #N/A | C19: {=XLOOKUP($A19,'企業名單'!$B:$B,'企業名單'!E:E)} -> #N/A | D19: {=XLOOKUP($A19,'企業名單'!$B:$B,'企業名單'!F:F)} -> #N/A | E19: {=XLOOKUP($A19,'企業名單'!$B:$B,'企業名單'!G:G)} -> #N/A | H19: 台灣企業永續獎 台灣永續企業績優獎
A20: 中國鋼鐵股份有限公司 | B20: {=XLOOKUP($A20,'企業名單'!$B:$B,'企業名單'!D:D)} -> #N/A | C20: {=XLOOKUP($A20,'企業名單'!$B:$B,'企業名單'!E:E)} -> #N/A | D20: {=XLOOKUP($A20,'企業名單'!$B:$B,'企業名單'!F:F)} -> #N/A | E20: {=XLOOKUP($A20,'企業名單'!$B:$B,'企業名單'!G:G)} -> #N/A | H20: 台灣企業永續獎 台灣十大永續典範企業獎 | I20: 台灣企業永續獎 單項績效 - 氣候領袖獎
A21: 台達化學工業股份有限公司 | B21: {=XLOOKUP($A21,'企業名單'!$B:$B,'企業名單'!D:D)} -> #N/A | C21: {=XLOOKUP($A21,'企業名單'!$B:$B,'企業名單'!E:E)} -> #N/A | D21: {=XLOOKUP($A21,'企業名單'!$B:$B,'企業名單'!F:F)} -> #N/A | E21: {=XLOOKUP($A21,'企業名單'!$B:$B,'企業名單'!G:G)} -> #N/A | H21: 台灣企業永續獎 台灣100大永續典範企業獎
A22: 台橡股份有限公司 | B22: {=XLOOKUP($A22,'企業名單'!$B:$B,'企業名單'!D:D)} -> #N/A | C22: {=XLOOKUP($A22,'企業名單'!$B:$B,'企業名單'!E:E)} -> #N/A | D22: {=XLOOKUP($A22,'企業名單'!$B:$B,'企業名單'!F:F)} -> #N/A | E22: {=XLOOKUP($A22,'企業名單'!$B:$B,'企業名單'!G:G)} -> #N/A | H22: 台灣企業永續獎 台灣100大永續典範企業獎
A23: 台灣中油股份有限公司 | B23: {=XLOOKUP($A23,'企業名單'!$B:$B,'企業名單'!D:D)} -> #N/A | C23: {=XLOOKUP($A23,'企業名單'!$B:$B,'企業名單'!E:E)} -> #N/A | D23: {=XLOOKUP($A23,'企業名單'!$B:$B,'企業名單'!F:F)} -> #N/A | E23: {=XLOOKUP($A23,'企業名單'!$B:$B,'企業名單'!G:G)} -> #N/A | H23: 台灣企業永續獎 台灣100大永續典範企業獎 | I23: 台灣企業永續獎 單項績效 - 氣候領袖獎
A24: 台灣玻璃工業股份有限公司 | B24: {=XLOOKUP($A24,'企業名單'!$B:$B,'企業名單'!D:D)} -> #N/A | C24: {=XLOOKUP($A24,'企業名單'!$B:$B,'企業名單'!E:E)} -> #N/A | D24: {=XLOOKUP($A24,'企業名單'!$B:$B,'企業名單'!F:F)} -> #N/A | E24: {=XLOOKUP($A24,'企業名單'!$B:$B,'企業名單'!G:G)} -> #N/A | H24: 台灣企業永續獎 台灣永續企業績優獎
A25: 台灣聚合化學品股份有限公司 | B25: {=XLOOKUP($A25,'企業名單'!$B:$B,'企業名單'!D:D)} -> #N/A | C25: {=XLOOKUP($A25,'企業名單'!$B:$B,'企業名單'!E:E)} -> #N/A | D25: {=XLOOKUP($A25,'企業名單'!$B:$B,'企業名單'!F:F)} -> #N/A | E25: {=XLOOKUP($A25,'企業名單'!$B:$B,'企業名單'!G:G)} -> #N/A | H25: 台灣企業永續獎 台灣永續企業績優獎
A26: 台灣糖業股份有限公司 | B26: {=XLOOKUP($A26,'企業名單'!$B:$B,'企業名單'!D:D)} -> #N/A | C26: {=XLOOKUP($A26,'企業名單'!$B:$B,'企業名單'!E:E)} -> #N/A | D26: {=XLOOKUP($A26,'企業名單'!$B:$B,'企業名單'!F:F)} -> #N/A | E26: {=XLOOKUP($A26,'企業名單'!$B:$B,'企業名單'!G:G)} -> #N/A | H26: 台灣企業永續獎 台灣100大永續典範企業獎
A27: 正隆股份有限公司 | B27: {=XLOOKUP($A27,'企業名單'!$B:$B,'企業名單'!D:D)} -> #N/A | C27: {=XLOOKUP($A27,'企業名單'!$B:$B,'企業名單'!E:E)} -> #N/A | D27: {=XLOOKUP($A27,'企業名單'!$B:$B,'企業名單'!F:F)} -> #N/A | E27: {=XLOOKUP($A27,'企業名單'!$B:$B,'企業名單'!G:G)} -> #N/A | F27: 企業類永續發展獎（大園廠） | H27: 台灣企業永續獎 台灣100大永續典範企業獎 | J27: 大型企業
A28: 永豐餘消費品實業股份有限公司 | B28: {=XLOOKUP($A28,'企業名單'!$B:$B,'企業名單'!D:D)} -> #N/A | C28: {=XLOOKUP($A28,'企業名單'!$B:$B,'企業名單'!E:E)} -> #N/A | D28: {=XLOOKUP($A28,'企業名單'!$B:$B,'企業名單'!F:F)} -> #N/A | E28: {=XLOOKUP($A28,'企業名單'!$B:$B,'企業名單'!G:G)} -> #N/A | H28: 台灣企業永續獎 台灣永續企業績優獎
A29: 合晶科技股份有限公司 | B29: {=XLOOKUP($A29,'企業名單'!$B:$B,'企業名單'!D:D)} -> #N/A | C29: {=XLOOKUP($A29,'企業名單'!$B:$B,'企業名單'!E:E)} -> #N/A | D29: {=XLOOKUP($A29,'企業名單'!$B:$B,'企業名單'!F:F)} -> #N/A | E29: {=XLOOKUP($A29,'企業名單'!$B:$B,'企業名單'!G:G)} -> #N/A | H29: 台灣企業永續獎 台灣永續企業績優獎
A30: 宏全國際股份有限公司 | B30: {=XLOOKUP($A30,'企業名單'!$B:$B,'企業名單'!D:D)} -> #N/A | C30: {=XLOOKUP($A30,'企業名單'!$B:$B,'企業名單'!E:E)} -> #N/A | D30: {=XLOOKUP($A30,'企業名單'!$B:$B,'企業名單'!F:F)} -> #N/A | E30: {=XLOOKUP($A30,'企業名單'!$B:$B,'企業名單'!G:G)} -> #N/A | H30: 台灣企業永續獎 台灣永續企業績優獎
A31: 宏遠興業股份有限公司 | B31: {=XLOOKUP($A31,'企業名單'!$B:$B,'企業名單'!D:D)} -> #N/A | C31: {=XLOOKUP($A31,'企業名單'!$B:$B,'企業名單'!E:E)} -> #N/A | D31: {=XLOOKUP($A31,'企業名單'!$B:$B,'企業名單'!F:F)} -> #N/A | E31: {=XLOOKUP($A31,'企業名單'!$B:$B,'企業名單'!G:G)} -> #N/A | H31: 台灣企業永續獎 台灣永續企業績優獎
A32: 亞洲聚合股份有限公司 | B32: {=XLOOKUP($A32,'企業名單'!$B:$B,'企業名單'!D:D)} -> #N/A | C32: {=XLOOKUP($A32,'企業名單'!$B:$B,'企業名單'!E:E)} -> #N/A | D32: {=XLOOKUP($A32,'企業名單'!$B:$B,'企業名單'!F:F)} -> #N/A | E32: {=XLOOKUP($A32,'企業名單'!$B:$B,'企業名單'!G:G)} -> #N/A | H32: 台灣企業永續獎 台灣100大永續典範企業獎
A33: 東聯化學股份有限公司 | B33: {=XLOOKUP($A33,'企業名單'!$B:$B,'企業名單'!D:D)} -> #N/A | C33: {=XLOOKUP($A33,'企業名單'!$B:$B,'企業名單'!E:E)} -> #N/A | D33: {=XLOOKUP($A33,'企業名單'!$B:$B,'企業名單'!F:F)} -> #N/A | E33: {=XLOOKUP($A33,'企業名單'!$B:$B,'企業名單'!G:G)} -> #N/A | H33: 台灣企業永續獎 台灣永續企業績優獎
A34: 欣興電子股份有限公司 | B34: {=XLOOKUP($A34,'企業名單'!$B:$B,'企業名單'!D:D)} -> #N/A | C34: {=XLOOKUP($A34,'企業名單'!$B:$B,'企業名單'!E:E)} -> #N/A | D34: {=XLOOKUP($A34,'企業名單'!$B:$B,'企業名單'!F:F)} -> #N/A | E34: {=XLOOKUP($A34,'企業名單'!$B:$B,'企業名單'!G:G)} -> #N/A | H34: 台灣企業永續獎 台灣永續企業績優獎
A35: 南茂科技股份有限公司 | B35: {=XLOOKUP($A35,'企業名單'!$B:$B,'企業名單'!D:D)} -> #N/A | C35: {=XLOOKUP($A35,'企業名單'!$B:$B,'企業名單'!E:E)} -> #N/A | D35: {=XLOOKUP($A35,'企業名單'!$B:$B,'企業名單'!F:F)} -> #N/A | E35: {=XLOOKUP($A35,'企業名單'!$B:$B,'企業名單'!G:G)} -> #N/A | F35: 企業類永續發展獎 | H35: 台灣企業永續獎 台灣100大永續典範企業獎
A36: 華夏海灣塑膠股份有限公司 | B36: {=XLOOKUP($A36,'企業名單'!$B:$B,'企業名單'!D:D)} -> #N/A | C36: {=XLOOKUP($A36,'企業名單'!$B:$B,'企業名單'!E:E)} -> #N/A | D36: {=XLOOKUP($A36,'企業名單'!$B:$B,'企業名單'!F:F)} -> #N/A | E36: {=XLOOKUP($A36,'企業名單'!$B:$B,'企業名單'!G:G)} -> #N/A | H36: 台灣企業永續獎 台灣100大永續典範企業獎
A37: 華新麗華股份有限公司 | B37: {=XLOOKUP($A37,'企業名單'!$B:$B,'企業名單'!D:D)} -> #N/A | C37: {=XLOOKUP($A37,'企業名單'!$B:$B,'企業名單'!E:E)} -> #N/A | D37: {=XLOOKUP($A37,'企業名單'!$B:$B,'企業名單'!F:F)} -> #N/A | E37: {=XLOOKUP($A37,'企業名單'!$B:$B,'企業名單'!G:G)} -> #N/A | H37: 台灣企業永續獎 台灣100大永續典範企業獎
A38: 榮成紙業股份有限公司 | B38: {=XLOOKUP($A38,'企業名單'!$B:$B,'企業名單'!D:D)} -> #N/A | C38: {=XLOOKUP($A38,'企業名單'!$B:$B,'企業名單'!E:E)} -> #N/A | D38: {=XLOOKUP($A38,'企業名單'!$B:$B,'企業名單'!F:F)} -> #N/A | E38: {=XLOOKUP($A38,'企業名單'!$B:$B,'企業名單'!G:G)} -> #N/A | H38: 台灣企業永續獎 台灣永續企業績優獎
A39: 燿華電子股份有限公司 | B39: {=XLOOKUP($A39,'企業名單'!$B:$B,'企業名單'!D:D)} -> #N/A | C39: {=XLOOKUP($A39,'企業名單'!$B:$B,'企業名單'!E:E)} -> #N/A | D39: {=XLOOKUP($A39,'企業名單'!$B:$B,'企業名單'!F:F)} -> #N/A | E39: {=XLOOKUP($A39,'企業名單'!$B:$B,'企業名單'!G:G)} -> #N/A | H39: 台灣企業永續獎 台灣永續企業績優獎

Sheet 所有排碳大戶_2024_300
A1: 公司
A2: 台灣電力股份有限公司
A3: 台塑石化股份有限公司
A4: 中國鋼鐵股份有限公司
A5: 台灣積體電路製造股份有限公司
A6: 麥寮汽電股份有限公司
A7: 中龍鋼鐵股份有限公司
A8: 台灣化學纖維股份有限公司
A9: 台灣塑膠工業股份有限公司
A10: 和平電力股份有限公司
A11: 台灣中油股份有限公司
A12: 南亞塑膠工業股份有限公司
... A301: 南中石化工業股份有限公司
